pysimsimi/__init__.py
pysimsimi/simitalk.py
pysimsimi/simiteach.py
pysimsimi-1.0.1.dist-info/LICENSE
pysimsimi-1.0.1.dist-info/METADATA
pysimsimi-1.0.1.dist-info/WHEEL
pysimsimi-1.0.1.dist-info/top_level.txt
pysimsimi-1.0.1.dist-info/RECORD
